player/__init__.py
player/player.py
playerjechmx-0.0.1.dist-info/METADATA
playerjechmx-0.0.1.dist-info/WHEEL
playerjechmx-0.0.1.dist-info/top_level.txt
playerjechmx-0.0.1.dist-info/RECORD
