Metadata-Version: 2.1
Name: playerjechmx
Version: 0.0.1
Summary: reproductor de musica
Author: Jose Chavez
Author-email: jechmx1@gmail.com
